Metadata-Version: 1.1
Name: didsho
Version: 1.5
Summary: Didsho SDK for python telegram bot @didshobot
Home-page: https://github.com/mdisepehr/didshoPython
Author: Sadeq Hajizadeh
Author-email: sadegh.h.2007@hotmail.com
License: FREE TO USE
Keywords: didsho sdk didshoPython didshosdk
Platform: UNKNOWN
Classifier: Development Status :: 5 - Production/Stable
Classifier: License :: Freely Distributable
Classifier: Programming Language :: Python :: 2.7
Classifier: Topic :: Software Development :: Libraries
